CHANGELOG.txt
LICENSE.txt
MANIFEST.in
README.rst
setup.py
pixel_zero.egg-info/PKG-INFO
pixel_zero.egg-info/SOURCES.txt
pixel_zero.egg-info/dependency_links.txt
pixel_zero.egg-info/requires.txt
pixel_zero.egg-info/top_level.txt
pixelzero/__init__.py